README.rst
setup.py
pyhistogram/__init__.py
pyhistogram/axis.py
pyhistogram/bin_container.py
pyhistogram/bin_proxy.py
pyhistogram/datetime_tmp.py
pyhistogram/flow_exceptions.py
pyhistogram/hist.py
pyhistogram/utils.py
pyhistogram.egg-info/PKG-INFO
pyhistogram.egg-info/SOURCES.txt
pyhistogram.egg-info/dependency_links.txt
pyhistogram.egg-info/requires.txt
pyhistogram.egg-info/top_level.txt
pyhistogram/tests/__init__.py
pyhistogram/tests/axis_test.py
pyhistogram/tests/bin_container_test.py
pyhistogram/tests/bin_proxy_test.py
pyhistogram/tests/histogram_test.py
pyhistogram/tests/matplotlib_example.py