Metadata-Version: 1.1
Name: pyhistogram
Version: 0.1
Summary: Convinient and intuitive histograms with minimal dependencies
Home-page: https://github.com/chrisboo/pyhistogram
Author: Christian Bourjau
Author-email: c.bourjau@gmx.net
License: UNKNOWN
Download-URL: https://github.com/chrisboo/pyhistogram/tarball/0.1
Keywords: histogram,statistics
Platform: UNKNOWN
Classifier: Programming Language :: Python
Classifier: Programming Language :: Python :: 2.7
Classifier: License :: OSI Approved :: GNU General Public License v3 (GPLv3)
Classifier: Operating System :: OS Independent
Classifier: Intended Audience :: Developers
Classifier: Intended Audience :: Science/Research
Classifier: Topic :: Scientific/Engineering :: Mathematics
Classifier: Topic :: Scientific/Engineering :: Physics
Classifier: Development Status :: 3 - Alpha
Classifier: Topic :: Software Development :: Libraries :: Python Modules
